LICENSE
MANIFEST.in
README.md
setup.py
peakrdl/verilog/__about__.py
peakrdl/verilog/__init__.py
peakrdl/verilog/exporter.py
peakrdl/verilog/peakverilog.py
peakrdl/verilog/busses/native.impl.sv
peakrdl/verilog/busses/native.ports.sv
peakrdl/verilog/templates/addressable.sv
peakrdl/verilog/templates/module.sv
peakrdl/verilog/templates/register.sv
peakrdl/verilog/templates/tb.cpp
peakrdl/verilog/templates/tb.sv
peakrdl_verilog.egg-info/PKG-INFO
peakrdl_verilog.egg-info/SOURCES.txt
peakrdl_verilog.egg-info/dependency_links.txt
peakrdl_verilog.egg-info/requires.txt
peakrdl_verilog.egg-info/top_level.txt