Metadata-Version: 2.1
Name: peakrdl-verilog
Version: 1.0.0
Summary: Generate verilog register module from compiled SystemRDL input
Home-page: https://github.com/SystemRDL/PeakRDL-verilog
Author: Hugh Jackson
Project-URL: Source, https://github.com/SystemRDL/PeakRDL-verilog
Project-URL: Tracker, https://github.com/SystemRDL/PeakRDL-verilog/issues
Classifier: Development Status :: 5 - Production/Stable
Classifier: Programming Language :: Python
Classifier: Programming Language :: Python :: 3
Classifier: Programming Language :: Python :: 3.5
Classifier: Programming Language :: Python :: 3.6
Classifier: Programming Language :: Python :: 3.7
Classifier: Programming Language :: Python :: 3.8
Classifier: Programming Language :: Python :: 3 :: Only
Classifier: Intended Audience :: Developers
Classifier: License :: OSI Approved :: GNU General Public License v3 (GPLv3)
Classifier: Operating System :: OS Independent
Classifier: Topic :: Scientific/Engineering :: Electronic Design Automation (EDA)
License-File: LICENSE
